{
  "_instructions": {
    "folder_structure": "sessions/session-3/",
    "slides_folder": "sessions/session-3/slides/   ← Put PPT slide images here (JPG/PNG)",
    "images_folder": "sessions/session-3/images/   ← Put activity photos, lab pics here (JPG/PNG)",
    "slide_naming": "slide-01.jpg, slide-02.jpg ... (exported from Section2_Electronics.pptx)",
    "pdf_support": "Place a PDF as 'slides.pdf' in the slides folder for embedded PDF viewer",
    "how_to_export": "PowerPoint → File → Export → Change File Type → JPEG/PNG → Save All Slides"
  },

  "id": "session-3",
  "number": 3,
  "title": "Real Electronics — Build Your First Project",
  "subtitle": "LED Circuits, Arduino UNO & Simulation Tools",
  "date": "Session 03",
  "duration": "75 minutes",
  "phase": "Foundation",
  "color": "#00FF88",
  "icon": "🔬",
  "tags": ["LED Circuit", "Arduino UNO", "Microcontroller", "Wokwi", "Tinkercad", "Simulation"],
  "overview": "From circuit theory to your first working project! We go from paper diagrams to real breadboard circuits. Understand how current flows, meet Arduino UNO, and learn to simulate before you build.",

  "slides": {
    "_note": "Export slides from 'Section2_Electronics.pptx' as JPEG/PNG into sessions/session-3/slides/",
    "pdf": "sessions/session-3/slides/slides.pdf",
    "_pdf_note": "Alternatively place your exported PDF here. The viewer supports both image slides and PDF.",
    "images": [
      {
        "file": "sessions/session-3/slides/slide-01.jpg",
        "_placeholder": "Export slide 1 from Section2_Electronics.pptx",
        "title": "Section 2: Real Electronics",
        "caption": "From circuit theory to your first working project"
      },
      {
        "file": "sessions/session-3/slides/slide-02.jpg",
        "_placeholder": "Export slide 2 from Section2_Electronics.pptx",
        "title": "Small Circuit, Big Magic!",
        "caption": "Battery → Resistor → LED → back to Battery"
      },
      {
        "file": "sessions/session-3/slides/slide-03.jpg",
        "_placeholder": "Export slide 3 from Section2_Electronics.pptx",
        "title": "How Current Flows Through a Circuit",
        "caption": "Electricity travels in a CLOSED LOOP"
      },
      {
        "file": "sessions/session-3/slides/slide-04.jpg",
        "_placeholder": "Export slide 4 from Section2_Electronics.pptx",
        "title": "Meet Arduino UNO",
        "caption": "14 Digital I/O Pins | 6 Analog Inputs | USB Connection | 5V"
      },
      {
        "file": "sessions/session-3/slides/slide-05.jpg",
        "_placeholder": "Export slide 5 from Section2_Electronics.pptx",
        "title": "Microcontroller vs Microprocessor",
        "caption": "MCU = CPU+Memory+I/O in one | MPU = CPU only"
      },
      {
        "file": "sessions/session-3/slides/slide-06.jpg",
        "_placeholder": "Export slide 6 from Section2_Electronics.pptx",
        "title": "Why Do Engineers Use Arduino?",
        "caption": "Open-source, affordable, beginner-friendly, used worldwide"
      },
      {
        "file": "sessions/session-3/slides/slide-07.jpg",
        "_placeholder": "Export slide 7 from Section2_Electronics.pptx",
        "title": "How We Communicate with Arduino",
        "caption": "Arduino IDE | Wokwi | Tinkercad"
      },
      {
        "file": "sessions/session-3/slides/slide-08.jpg",
        "_placeholder": "Export slide 8 from Section2_Electronics.pptx",
        "title": "Simulate Before You Build",
        "caption": "No component damage | Zero cost | Easy debugging | Faster iteration"
      },
      {
        "file": "sessions/session-3/slides/slide-09.jpg",
        "_placeholder": "Export slide 9 from Section2_Electronics.pptx",
        "title": "From Idea to Working Project",
        "caption": "01 IDEA → 02 SIMULATE → 03 BUILD → 04 PRESENT"
      },
      {
        "file": "sessions/session-3/slides/slide-10.jpg",
        "_placeholder": "Export slide 10 from Section2_Electronics.pptx",
        "title": "Session Wrap-Up — You Are Now an Engineer!",
        "caption": "LED circuit ✓ | Current flow ✓ | Arduino UNO ✓ | MCU vs MPU ✓ | Wokwi ✓"
      }
    ]
  },

  "images": {
    "_note": "Add photos from this session — Arduino board, Wokwi screenshots, student circuits, simulation screenshots.",
    "gallery": [
      {
        "file": "sessions/session-3/images/img-01.jpg",
        "_placeholder": "ADD: Photo of Arduino UNO board close-up with labels",
        "caption": "Arduino UNO — labelled pins and ports",
        "category": "Components"
      },
      {
        "file": "sessions/session-3/images/img-02.jpg",
        "_placeholder": "ADD: Screenshot of Wokwi simulator with LED circuit",
        "caption": "Wokwi Simulator — LED blink circuit",
        "category": "Simulation"
      },
      {
        "file": "sessions/session-3/images/img-03.jpg",
        "_placeholder": "ADD: Screenshot of Tinkercad circuit builder",
        "caption": "Tinkercad — visual circuit builder",
        "category": "Simulation"
      },
      {
        "file": "sessions/session-3/images/img-04.jpg",
        "_placeholder": "ADD: Photo of real breadboard LED circuit with Arduino",
        "caption": "Real breadboard circuit with Arduino UNO",
        "category": "Activity"
      },
      {
        "file": "sessions/session-3/images/img-05.jpg",
        "_placeholder": "ADD: Photo of Arduino IDE on screen with blink code",
        "caption": "Arduino IDE — writing the first blink program",
        "category": "Code"
      },
      {
        "file": "sessions/session-3/images/img-06.jpg",
        "_placeholder": "ADD: Photo of students uploading code to Arduino",
        "caption": "Uploading code via USB — LED blinks!",
        "category": "Lab"
      }
    ]
  },

  "keyTopics": [
    "LED Circuit — Battery + Resistor + LED complete loop",
    "How Current Flows in a Complete Loop (open = stops)",
    "Arduino UNO — 14 Digital I/O, 6 Analog, USB, 5V",
    "Microcontroller vs Microprocessor — What's the difference?",
    "Why Engineers Use Arduino — open-source, affordable",
    "Simulation Tools: Arduino IDE, Wokwi, Tinkercad",
    "Simulate Before You Build — Industry Best Practice",
    "Engineering Process: Idea → Simulate → Build → Present"
  ],

  "youtubeVideos": [
    {
      "title": "Arduino UNO Tutorial for Beginners",
      "videoId": "fJWR7dBuc18",
      "_note": "Replace videoId with actual YouTube video ID",
      "desc": "Complete guide to getting started with Arduino UNO."
    },
    {
      "title": "Wokwi Arduino Simulator Tutorial",
      "videoId": "qmt49NPp1mQ",
      "desc": "Learn to use the free Wokwi online simulator."
    },
    {
      "title": "How to Build an LED Circuit",
      "videoId": "CfdaJ4z4u4w",
      "desc": "Step-by-step LED circuit on breadboard with Arduino."
    }
  ],

  "resources": [
    {
      "title": "Wokwi Arduino Simulator",
      "url": "https://wokwi.com",
      "icon": "🔗",
      "_note": "Add any website URL here. icon can be any emoji."
    },
    {
      "title": "Tinkercad Circuits",
      "url": "https://www.tinkercad.com/circuits",
      "icon": "🔗"
    },
    {
      "title": "Arduino IDE Download",
      "url": "https://www.arduino.cc/en/software",
      "icon": "🔗"
    },
    {
      "title": "Arduino Getting Started Guide",
      "url": "https://docs.arduino.cc/learn/starting-guide/getting-started-arduino",
      "icon": "📖"
    }
  ],

  "activity": {
    "title": "Simulate then Build — LED Blink with Arduino",
    "parts": [
      "Computer with browser (for Wokwi simulation)",
      "Arduino UNO (for real build)",
      "Breadboard",
      "LED",
      "220Ω Resistor",
      "USB cable",
      "Jumper wires"
    ],
    "steps": [
      "Step 1: Go to wokwi.com and open Arduino UNO template",
      "Step 2: Add LED and resistor in the simulation",
      "Step 3: Write the blink code (void setup / void loop)",
      "Step 4: Run simulation — see LED blink!",
      "Step 5: Now build the real circuit on breadboard",
      "Step 6: Upload code to real Arduino and watch it blink!"
    ]
  },

  "quiz": [
    {
      "q": "In a complete LED circuit, what happens when you disconnect one wire?",
      "options": [
        "The LED glows brighter",
        "Nothing changes",
        "The circuit loop breaks — LED goes off",
        "The resistor burns out"
      ],
      "answer": 2,
      "explanation": "Electricity needs a COMPLETE LOOP to flow. Break the loop (disconnect any wire) → current stops → LED off."
    },
    {
      "q": "Why is a resistor ESSENTIAL in an LED circuit?",
      "options": [
        "To make the LED glow different colours",
        "To limit current and protect the LED from burning out",
        "To increase the voltage",
        "To make the circuit look more complex"
      ],
      "answer": 1,
      "explanation": "Without a resistor, too much current flows through the LED and destroys it instantly. The resistor is the LED's bodyguard!"
    },
    {
      "q": "How many Digital I/O pins does Arduino UNO have?",
      "options": ["6", "8", "12", "14"],
      "answer": 3,
      "explanation": "Arduino UNO has 14 Digital I/O pins! These can be INPUT (read sensor) or OUTPUT (control LED, motor)."
    },
    {
      "q": "What operating voltage does Arduino UNO use?",
      "options": ["3.3V", "5V", "9V", "12V"],
      "answer": 1,
      "explanation": "Arduino UNO operates at 5V — safe for beginners! This is the voltage on digital pins when set to HIGH."
    },
    {
      "q": "What is the main difference between Microcontroller and Microprocessor?",
      "options": [
        "Microcontrollers are bigger",
        "Microcontroller has CPU+Memory+I/O all in one chip; Microprocessor only has CPU",
        "Microprocessors are cheaper",
        "They are exactly the same thing"
      ],
      "answer": 1,
      "explanation": "Microcontroller = All-in-one (CPU + Memory + I/O). Microprocessor = Just the CPU. That's why Arduino is a microcontroller!"
    },
    {
      "q": "Which chip is the Microcontroller inside Arduino UNO?",
      "options": [
        "Intel Core i7",
        "Apple M1 chip",
        "ATmega328P",
        "AMD Ryzen"
      ],
      "answer": 2,
      "explanation": "ATmega328P is the microcontroller chip inside Arduino UNO! It has everything needed to run programs and control hardware."
    },
    {
      "q": "What is Wokwi?",
      "options": [
        "A type of Arduino board",
        "A free online Arduino circuit simulator",
        "A brand of breadboard",
        "An electronics store"
      ],
      "answer": 1,
      "explanation": "Wokwi (wokwi.com) is a FREE browser-based Arduino simulator. Write code and test circuits virtually — no hardware needed!"
    },
    {
      "q": "What is Tinkercad used for in electronics?",
      "options": [
        "Only 3D printing",
        "A visual drag-and-drop circuit builder with code simulation",
        "Ordering electronic components",
        "Writing Arduino programs only"
      ],
      "answer": 1,
      "explanation": "Tinkercad Circuits lets you drag-and-drop components AND write code to simulate. Perfect for beginners!"
    },
    {
      "q": "Why do professional engineers simulate before building?",
      "options": [
        "Because they don't have real components",
        "To save time and money — mistakes in simulation are free",
        "Simulation is required by law",
        "Because real circuits don't work"
      ],
      "answer": 1,
      "explanation": "Simulate first = No component damage, zero cost for mistakes, easy debugging. Standard industry practice!"
    },
    {
      "q": "What is the correct engineering process order?",
      "options": [
        "Build → Simulate → Idea → Present",
        "Idea → Simulate → Build → Present",
        "Present → Build → Simulate → Idea",
        "Simulate → Idea → Present → Build"
      ],
      "answer": 1,
      "explanation": "01 IDEA → 02 SIMULATE → 03 BUILD → 04 PRESENT. Always simulate before touching real components!"
    },
    {
      "q": "What does Arduino IDE stand for?",
      "options": [
        "Integrated Development Environment",
        "International Digital Electronics",
        "Interactive Design Engine",
        "Input/Output Device Exchange"
      ],
      "answer": 0,
      "explanation": "IDE = Integrated Development Environment! Software where you write, compile, and upload Arduino code."
    },
    {
      "q": "How do you upload code to an Arduino?",
      "options": [
        "Using Bluetooth only",
        "Via USB connection from a computer",
        "By inserting a memory card",
        "Via WiFi only"
      ],
      "answer": 1,
      "explanation": "Connect Arduino to computer via USB, write code in Arduino IDE, click upload. Code sent through USB cable!"
    },
    {
      "q": "What does the LED convert electrical energy into?",
      "options": [
        "Sound",
        "Heat only",
        "Light (and a tiny amount of heat)",
        "Motion"
      ],
      "answer": 2,
      "explanation": "LED = Light Emitting Diode! Converts electrical energy into LIGHT. Very efficient at doing it!"
    },
    {
      "q": "What does 'open source' mean for Arduino?",
      "options": [
        "The box is open when you buy it",
        "The design and software are free for anyone to use, modify, and share",
        "It only works outdoors",
        "The code is secret"
      ],
      "answer": 1,
      "explanation": "Arduino is open-source! Hardware designs and software are free — anyone can use, modify, and share them."
    },
    {
      "q": "Before building a real circuit, what should you do FIRST?",
      "options": [
        "Buy all components",
        "Present your project",
        "Simulate on Wokwi or Tinkercad",
        "Write documentation"
      ],
      "answer": 2,
      "explanation": "Always SIMULATE first! Test digitally before building. Mistakes cost nothing in simulation!"
    }
  ]
}
